cook/__init__.py
cook/__main__.py
cook/file_server.py
cook/version.py
cook_file_server-0.1.0.dist-info/DESCRIPTION.rst
cook_file_server-0.1.0.dist-info/METADATA
cook_file_server-0.1.0.dist-info/RECORD
cook_file_server-0.1.0.dist-info/WHEEL
cook_file_server-0.1.0.dist-info/entry_points.txt
cook_file_server-0.1.0.dist-info/metadata.json
cook_file_server-0.1.0.dist-info/top_level.txt
