Metadata-Version: 2.0
Name: cook-file-server
Version: 0.1.0
Summary: Two Sigma's Cook File Server
Home-page: UNKNOWN
Author: UNKNOWN
Author-email: UNKNOWN
License: UNKNOWN
Platform: UNKNOWN
Requires-Dist: Flask (==1.1.0)
Requires-Dist: gunicorn (==19.9.0)
